funnelius/__init__.py
funnelius/functions.py
funnelius/interactive.polars.py
funnelius/interactive.py
funnelius-0.0.5.dist-info/licenses/LICENSE
funnelius-0.0.5.dist-info/METADATA
funnelius-0.0.5.dist-info/WHEEL
funnelius-0.0.5.dist-info/top_level.txt
funnelius-0.0.5.dist-info/RECORD
