Metadata-Version: 2.4
Name: funnelius
Version: 0.0.5
Summary: Funnelius is an open-source Python library designed to analyze and visualize complex, non-linear user funnels.
Author-email: Yaseen Esmaeelpour <yaseenes@gmail.com>
License-Expression: Apache-2.0
Project-URL: Homepage, https://github.com/yaseenesmaeelpour/funnelius
Project-URL: Issues, https://github.com/yaseenesmaeelpour/funnelius/issues
Keywords: funnel,journey,path,graph
Classifier: Programming Language :: Python :: 3
Classifier: Operating System :: OS Independent
Requires-Python: >=3.9
License-File: LICENSE
Requires-Dist: pandas>=2.2.3
Requires-Dist: numpy>=2.2.5
Requires-Dist: streamlit>=1.44.1
Requires-Dist: graphviz>=0.20.3
Requires-Dist: polars>=1.3.0
Dynamic: license-file
